cattr/__init__.py
cattr/_compat.py
cattr/converters.py
cattr/disambiguators.py
cattr/function_dispatch.py
cattr/multistrategy_dispatch.py
jw_cattrs-1.0.1.dist-info/LICENSE
jw_cattrs-1.0.1.dist-info/METADATA
jw_cattrs-1.0.1.dist-info/WHEEL
jw_cattrs-1.0.1.dist-info/top_level.txt
jw_cattrs-1.0.1.dist-info/RECORD
